[
    {
      "id": 1,
      "path": "/images/ExerciseImages/InclineBicepCurl.gif",
      "alt": "Incline Bicep Curl",
      "date":"10/3/2023",
      "text": "Bad Exercise",
      "exercise-group-id": 4,
      "exercise-id": 1,
      "rating": 2
      
    },
    {
      "id": 2,
      "path": "/images/ExerciseImages/ConcentrationCurl.gif",
      "alt": "Concentration Curl",
      "text": "Trash exercise",
      "date":"10/3/2023",
      "exercise-group-id": 5,
      "exercise-id": 2,
      "rating": 4
    }
    
  ]
  